Metadata-Version: 2.4
Name: pymesh2d
Version: 0.1.8.dev0
Summary: pymesh2D is a Python-based unstructured mesh-generator for two-dimensional polygonal geometries, providing a range of relatively simple, yet effective two-dimensional meshing algorithms.
Author-email: Geomatics and Ocean Engineering Group <faugeree@unican.es>
License:                     GNU GENERAL PUBLIC LICENSE
Project-URL: Homepage, https://github.com/GeoOcean/pymesh2d
Project-URL: Documentation, https://github.com/GeoOcean/pymesh2d
Project-URL: Issues, https://github.com/GeoOcean/pymesh2d/issues
Keywords: mesh
Classifier: Programming Language :: Python :: 3 :: Only
Classifier: License :: OSI Approved :: GNU General Public License v3 (GPLv3)
Classifier: Programming Language :: Python :: 3.7
Classifier: Programming Language :: Python :: 3.8
Classifier: Programming Language :: Python :: 3.9
Classifier: Programming Language :: Python :: 3.10
Classifier: Programming Language :: Python :: 3.11
Classifier: Programming Language :: Python :: 3.12
Classifier: Programming Language :: Python :: 3.13
Classifier: Programming Language :: Python :: 3.14
Requires-Python: >=3.7
License-File: LICENSE
Requires-Dist: numpy
Requires-Dist: scipy
Requires-Dist: matplotlib
Requires-Dist: netCDF4
Requires-Dist: rasterio
Requires-Dist: xarray
Requires-Dist: shapely
Provides-Extra: geo
Requires-Dist: shapely; extra == "geo"
Dynamic: license-file
